githubanalysis/__init__.py
githubanalysis/cli.py
githubanalysis/analysis/__init__.py
githubanalysis/analysis/code_analyzer.py
githubanalysis/core/__init__.py
githubanalysis/core/challenge_detector.py
githubanalysis/core/commit_clusterer.py
githubanalysis/core/contributor_analyzer.py
githubanalysis/core/enhanced_git_analyzer.py
githubanalysis/core/impact_analyzer.py
githubanalysis/core/milestone_detector.py
githubanalysis/core/technical_challenge_detector.py
githubanalysis/llm/__init__.py
githubanalysis/llm/llm_analyzer.py
githubanalysis/llm/report_generator.py
githubanalysis/llm/prompts/default_prompts.json
githubanalysis-0.1.6.dist-info/LICENSE
githubanalysis-0.1.6.dist-info/METADATA
githubanalysis-0.1.6.dist-info/WHEEL
githubanalysis-0.1.6.dist-info/entry_points.txt
githubanalysis-0.1.6.dist-info/top_level.txt
githubanalysis-0.1.6.dist-info/RECORD
