Metadata-Version: 2.1
Name: githubanalysis
Version: 0.1.6
Summary: A powerful tool for analyzing Git repositories using LLM-powered insights
Author: Rimon
Author-email: info@rimon.com.au
Keywords: git,analysis,repository,llm,openai,gpt,commit,log,analysis
Classifier: Development Status :: 4 - Beta
Classifier: Intended Audience :: Developers
Classifier: Topic :: Software Development :: Version Control :: Git
Classifier: Programming Language :: Python :: 3
Classifier: License :: OSI Approved :: MIT License
Classifier: Operating System :: OS Independent
Requires-Python: >=3.7
License-File: LICENSE
Requires-Dist: gitpython >=3.1.42
Requires-Dist: numpy >=1.23.0
Requires-Dist: scikit-learn >=1.2.0
Requires-Dist: nltk >=3.8.0
Requires-Dist: requests >=2.28.0
Requires-Dist: openai >=1.0.0
Requires-Dist: tiktoken >=0.5.0
Requires-Dist: python-dotenv >=1.0.0
Requires-Dist: tqdm >=4.65.0
Requires-Dist: markdown >=3.3.0
Requires-Dist: pandas >=2.0.0
Requires-Dist: matplotlib >=3.7.0
Requires-Dist: seaborn >=0.12.0
